fastapix/__init__.py
fastapix/__main__.py
fastapix/exceptions.py
fastapix/handlers.py
fastapix/responses.py
fastapix/crud/__init__.py
fastapix/crud/_abc_database.py
fastapix/crud/_abc_database.pyi
fastapix/crud/_models.py
fastapix/crud/_router.py
fastapix/crud/_selecter.py
fastapix/crud/_sqlalchemy.py
fastapix/crud/_sqlmodel.py
fastapix/crud/_sqltypes.py
fastapix/crud/database.py
fastapix/crud/middleware.py
fastapix/crud/mixins/__init__.py
fastapix/crud/mixins/_typing.py
fastapix/crud/mixins/models.py
fastapix/pkg/__init__.py
fastapix/pkg/json.py
fastapix/pkg/markdown.py
fastapix/pkg/openapi/__init__.py
fastapix/pkg/openapi/scalar.py
fastapix/pkg/openapi/swagger.py
fastapix/pkg/openapi/static/__init__.py
fastapix/pkg/openapi/static/scalar-ui.js
fastapix/pkg/openapi/static/scalar-ui.js.map
fastapix/pkg/openapi/static/swagger-ui-bundle.js
fastapix/pkg/openapi/static/swagger-ui-bundle.js.map
fastapix/pkg/openapi/static/swagger-ui.css
fastapix/pkg/openapi/static/swagger-ui.css.map
fastapix/pkg/pydantic/__init__.py
fastapix/pkg/pydantic/_main.py
fastapix/pkg/pydantic/_url.py
fastapix/pkg/pydantic/settings/__init__.py
fastapix/pkg/pydantic/settings/_secrets.py
fastapix/pkg/pydantic/settings/yamlx/__init__.py
fastapix/pkg/pydantic/settings/yamlx/_include.py
fastapix/pkg/pydantic/settings/yamlx/_settings.py
fastapix_py-0.12.0.dist-info/METADATA
fastapix_py-0.12.0.dist-info/WHEEL
fastapix_py-0.12.0.dist-info/entry_points.txt
fastapix_py-0.12.0.dist-info/licenses/LICENSE
fastapix_py-0.12.0.dist-info/RECORD
