Metadata-Version: 2.4
Name: fastapix-py
Version: 0.12.0
Summary: A FastAPI plugin that quickly builds CRUD-API based on SQLAlchemy
Project-URL: Homepage, https://gitcode.com/zhangzhanqi/fastapix
Project-URL: Repository, https://gitcode.com/zhangzhanqi/fastapix
Project-URL: Source, https://gitcode.com/zhangzhanqi/fastapix
Author-email: zhangzhanqi <zzq120203@163.com>
License-Expression: Apache-2.0
License-File: LICENSE
Requires-Python: >=3.7
Requires-Dist: fastapi
Requires-Dist: loguru
Requires-Dist: pydantic[email]
Requires-Dist: sqlmodel>=0.0.14
Requires-Dist: uvicorn[standard]
